skpipes/__init__.py
skpipes/_version.py
skpipes/pipeline.py
skpipes/config/__init__.py
skpipes/config/categorical.py
skpipes/config/numerical.py
skpipes/config/preprocessing.py
scikit_pipes-0.0.1.dev2.dist-info/LICENSE
scikit_pipes-0.0.1.dev2.dist-info/METADATA
scikit_pipes-0.0.1.dev2.dist-info/WHEEL
scikit_pipes-0.0.1.dev2.dist-info/top_level.txt
scikit_pipes-0.0.1.dev2.dist-info/RECORD
