Metadata-Version: 2.1
Name: scikit-pipes
Version: 0.0.1.dev2
Summary: Scikit-Learn useful pre-defined Pipelines Hub
Home-page: https://github.com/rodrigo-arenas/scikit-pipes
Author: Rodrigo Arenas
Author-email: rodrigo.arenas456@gmail.com
License: MIT
Project-URL: Documentation, https://scikit-pipes.readthedocs.io/en/stable/
Project-URL: Source Code, https://github.com/rodrigo-arenas/scikit-pipes
Project-URL: Bug Tracker, https://github.com/rodrigo-arenas/scikit-pipes/issues
Platform: UNKNOWN
Classifier: License :: OSI Approved :: MIT License
Classifier: Programming Language :: Python :: 3
Classifier: Programming Language :: Python :: 3.7
Classifier: Programming Language :: Python :: 3.8
Classifier: Programming Language :: Python :: 3.9
Requires-Python: >=3.7
License-File: LICENSE
Requires-Dist: scikit-learn (>=0.21.3)
Requires-Dist: numpy (>=1.14.5)
